wordpress_recommender/README.md
wordpress_recommender/__init__.py
wordpress_recommender/common/embedding_utils.py
wordpress_recommender/configs.py
wordpress_recommender/content_extractors/sitemap_content_extractor.py
wordpress_recommender/index_creators/chroma_index_creator.py
wordpress_recommender/main.py
wordpress_recommender/retrievers/chroma_index_retriever.py
wordpress_recommender/utils.py
wordpress_recommender-0.1.3.dist-info/LICENSE
wordpress_recommender-0.1.3.dist-info/METADATA
wordpress_recommender-0.1.3.dist-info/WHEEL
wordpress_recommender-0.1.3.dist-info/entry_points.txt
wordpress_recommender-0.1.3.dist-info/RECORD
