Metadata-Version: 2.1
Name: wordpress-recommender
Version: 0.1.3
Summary: An application to recommend articles from a Wordpress blog based on user's query using semantic search
Author: Anurag Chatterjee
Requires-Python: >=3.9,<4.0
Classifier: Programming Language :: Python :: 3
Classifier: Programming Language :: Python :: 3.9
Classifier: Programming Language :: Python :: 3.10
Classifier: Programming Language :: Python :: 3.11
Requires-Dist: beautifulsoup4 (>=4.12.2)
Requires-Dist: chromadb (>=0.4.13)
Requires-Dist: langchain (>=0.0.262)
Requires-Dist: pandas (>=2.1.0)
Requires-Dist: sentence-transformers (>=2.2.2)
Requires-Dist: tiktoken (>=0.4.0)
Requires-Dist: typer[all] (>=0.9.0)
